beta/__init__.py
beta/cli.py
beta/utils.py
beta/core/__init__.py
beta/core/corelib.py
beta/core/expr_combine.py
beta/core/fileformat_check.py
beta/core/opt_validator.py
beta/core/permp.py
beta/core/pscore.py
beta/core/runbeta.py
beta/core/up_down_distance.py
beta/core/up_down_score.py
beta/motif/__init__.py
beta/motif/bayesian_motif_comp.py
beta/motif/fastafrombed.py
beta/motif/motif_clustering.py
beta/motif/motif_parser.py
beta/motif/motif_scan.py
beta/references/Entrez_Symbol_DBD.txt
beta/references/cistrome.db
beta/references/cistrome.xml
beta/references/hg18.refseq
beta/references/hg19.refseq
beta/references/hg19_CTCF_bound.bed
beta/references/hg38.refseq
beta/references/mm10.refseq
beta/references/mm9.refseq
beta/references/mm9_CTCF_bound.bed
beta/templates/motiflogos.zip
beta/templates/script.js
beta/templates/styles.css
beta/templates/subtemplate.html
beta/templates/template.html
beta_binding_analysis-2.1.1.dist-info/METADATA
beta_binding_analysis-2.1.1.dist-info/WHEEL
beta_binding_analysis-2.1.1.dist-info/entry_points.txt
beta_binding_analysis-2.1.1.dist-info/top_level.txt
beta_binding_analysis-2.1.1.dist-info/RECORD
