Metadata-Version: 2.4
Name: beta-binding-analysis
Version: 2.1.1
Summary: BETA: Binding and Expression Target Analysis - Integrative analysis of ChIP-seq and RNA-seq data
Author-email: Su Wang <wangsu0623@gmail.com>, Tommy Tang <tangmig2005@gmail.com>
Maintainer-email: Tommy Tang <tangmig2005@gmail.com>
License: Artistic License 2.0
Project-URL: Homepage, http://cistrome.org/BETA
Project-URL: Documentation, http://cistrome.org/BETA/tutorial.html
Project-URL: Repository, https://github.com/yourusername/BETA2
Project-URL: Issues, https://github.com/yourusername/BETA2/issues
Keywords: bioinformatics,chip-seq,rna-seq,transcription-factors,gene-regulation,genomics
Classifier: Development Status :: 4 - Beta
Classifier: Environment :: Console
Classifier: Intended Audience :: Science/Research
Classifier: License :: OSI Approved :: Artistic License
Classifier: Operating System :: MacOS :: MacOS X
Classifier: Operating System :: POSIX :: Linux
Classifier: Programming Language :: Python :: 3
Classifier: Programming Language :: Python :: 3.8
Classifier: Programming Language :: Python :: 3.9
Classifier: Programming Language :: Python :: 3.10
Classifier: Programming Language :: Python :: 3.11
Classifier: Programming Language :: Python :: 3.12
Classifier: Topic :: Scientific/Engineering :: Bio-Informatics
Requires-Python: >=3.8
Requires-Dist: numpy>=1.20.0
Requires-Dist: scipy>=1.7.0
Requires-Dist: matplotlib>=3.3.0
Requires-Dist: setuptools>=61.0
Provides-Extra: dev
Requires-Dist: pytest>=7.0; extra == "dev"
Requires-Dist: pytest-cov>=3.0; extra == "dev"
Requires-Dist: black>=22.0; extra == "dev"
Requires-Dist: flake8>=4.0; extra == "dev"
Requires-Dist: mypy>=0.990; extra == "dev"
